Classfile /Users/payashi/Documents/java-playground/java-playground/target/classes/com/example/App.class
  Last modified Dec 29, 2024; size 563 bytes
  SHA-256 checksum 65147fcf061b477a8426bd124151d4ddde0f3411fc5b05ed9d200645d326ee79
  Compiled from "App.java"
public class com.example.App
  minor version: 0
  major version: 52
  flags: (0x0021) ACC_PUBLIC, ACC_SUPER
  this_class: #1                          // com/example/App
  super_class: #3                         // java/lang/Object
  interfaces: 0, fields: 0, methods: 2, attributes: 1
Constant pool:
   #1 = Class              #2             // com/example/App
   #2 = Utf8               com/example/App
   #3 = Class              #4             // java/lang/Object
   #4 = Utf8               java/lang/Object
   #5 = Utf8               <init>
   #6 = Utf8               ()V
   #7 = Utf8               Code
   #8 = Methodref          #3.#9          // java/lang/Object."<init>":()V
   #9 = NameAndType        #5:#6          // "<init>":()V
  #10 = Utf8               LineNumberTable
  #11 = Utf8               LocalVariableTable
  #12 = Utf8               this
  #13 = Utf8               Lcom/example/App;
  #14 = Utf8               main
  #15 = Utf8               ([Ljava/lang/String;)V
  #16 = Class              #17            // com/example/Hoge
  #17 = Utf8               com/example/Hoge
  #18 = Methodref          #16.#9         // com/example/Hoge."<init>":()V
  #19 = Methodref          #16.#20        // com/example/Hoge.hello:()V
  #20 = NameAndType        #21:#6         // hello:()V
  #21 = Utf8               hello
  #22 = Class              #23            // com/fuga/Fuga
  #23 = Utf8               com/fuga/Fuga
  #24 = Methodref          #22.#9         // com/fuga/Fuga."<init>":()V
  #25 = Methodref          #22.#20        // com/fuga/Fuga.hello:()V
  #26 = Utf8               args
  #27 = Utf8               [Ljava/lang/String;
  #28 = Utf8               hoge
  #29 = Utf8               Lcom/example/Hoge;
  #30 = Utf8               fuga
  #31 = Utf8               Lcom/fuga/Fuga;
  #32 = Utf8               SourceFile
  #33 = Utf8               App.java
{
  public com.example.App();
    descriptor: ()V
    flags: (0x0001) ACC_PUBLIC
    Code:
      stack=1, locals=1, args_size=1
         0: aload_0
         1: invokespecial #8                  // Method java/lang/Object."<init>":()V
         4: return
      LineNumberTable:
        line 5: 0
      LocalVariableTable:
        Start  Length  Slot  Name   Signature
            0       5     0  this   Lcom/example/App;

  public static void main(java.lang.String[]);
    descriptor: ([Ljava/lang/String;)V
    flags: (0x0009) ACC_PUBLIC, ACC_STATIC
    Code:
      stack=2, locals=3, args_size=1
         0: new           #16                 // class com/example/Hoge
         3: dup
         4: invokespecial #18                 // Method com/example/Hoge."<init>":()V
         7: astore_1
         8: aload_1
         9: invokevirtual #19                 // Method com/example/Hoge.hello:()V
        12: new           #22                 // class com/fuga/Fuga
        15: dup
        16: invokespecial #24                 // Method com/fuga/Fuga."<init>":()V
        19: astore_2
        20: aload_2
        21: invokevirtual #25                 // Method com/fuga/Fuga.hello:()V
        24: return
      LineNumberTable:
        line 7: 0
        line 8: 8
        line 9: 12
        line 10: 20
        line 11: 24
      LocalVariableTable:
        Start  Length  Slot  Name   Signature
            0      25     0  args   [Ljava/lang/String;
            8      17     1  hoge   Lcom/example/Hoge;
           20       5     2  fuga   Lcom/fuga/Fuga;
}
SourceFile: "App.java"
